{
    "burgers": [{
            "id": 1,
            "nom": "Burger royal",
            "prix": 1500,
            "image": "../../assets/images/burgers/burger-1.jpg"
        },
        {
            "id": 2,
            "nom": "Burger double",
            "prix": 2000,
            "image": "../../assets/images/burgers/burger-2.jpg"
        },
        {
            "id": 1,
            "nom": "Burger triple",
            "prix": 4500,
            "image": "../../assets/images/burgers/burger-3.jpeg"
        },
        {
            "id": 1,
            "nom": "Burger Senegal",
            "prix": 4500,
            "image": "../../assets/images/burgers/burger-4.jpg"
        },
        {
            "id": 1,
            "nom": "Burger adama",
            "prix": 4500,
            "image": "../../assets/images/burgers/burger-5.jpg"
        },
        {
            "id": 1,
            "nom": "Burger Der",
            "prix": 4500,
            "image": "../../assets/images/burgers/burger-6.jpg"
        }
    ],
    "menus": [{
            "id": 1,
            "nom": "Menu royal",
            "burgers": [],
            "boissons": [],
            "image": "../../assets/images/menus/menu-burger-1.jpeg",
            "prix": 1500
        },
        {
            "id": 1,
            "nom": "Menu double",
            "burgers": [],
            "boissons": [],
            "image": "../../assets/images/menus/menu-burger-2.jpg",
            "prix": 1500
        },
        {
            "id": 1,
            "nom": "Menu triple",
            "burgers": [],
            "boissons": [],
            "image": "../../assets/images/menus/menu-burger-2.jpg",
            "prix": 4500
        }
    ]
}